geordpy/__init__.py
geordpy/_version.py
geordpy/example.py
geordpy/geordpy.py
geordpy/great_circle.py
geordpy/rhumb_line.py
geordpy-3.1.dist-info/LICENSE
geordpy-3.1.dist-info/METADATA
geordpy-3.1.dist-info/WHEEL
geordpy-3.1.dist-info/top_level.txt
geordpy-3.1.dist-info/RECORD
