Metadata-Version: 2.1
Name: geordpy
Version: 3.1
Summary: A Python library for simplifying geodetic-coordinate polylines using the Ramer-Douglas-Peucker algorithm
Home-page: https://github.com/avitase/geordpy
Author: Nis Meinert
Author-email: mail@nismeinert.name
Requires-Python: >=3.10
License-File: LICENSE
Requires-Dist: numpy
Provides-Extra: dev
Requires-Dist: pre-commit ; extra == 'dev'
Requires-Dist: pytest ; extra == 'dev'
Requires-Dist: pytest-cov ; extra == 'dev'
Requires-Dist: sphinx ; extra == 'dev'
Requires-Dist: scipy ; extra == 'dev'
